pyexifpro/__init__.py
pyexifpro-0.0.1.dist-info/LICENSE
pyexifpro-0.0.1.dist-info/METADATA
pyexifpro-0.0.1.dist-info/WHEEL
pyexifpro-0.0.1.dist-info/top_level.txt
pyexifpro-0.0.1.dist-info/RECORD
